{
 "type": "FeatureCollection",
 "features": [
  {
   "type": "Feature",
   "id": "way/446233195",
   "properties": {
    "leisure": "pitch",
    "name": "Sint Donatius Gilde",
    "sport": "archery",
    "surface": "grass",
    "id": "way/446233195",
    "_lat": "51.09155105",
    "_lon": "4.3035977",
    "_surface": "652.9609475334678",
    "_surface:ha": "0",
    "_length": "103.29541972317652",
    "_length:km": "0.1",
    "_last_edit:contributor": "Rienux",
    "_last_edit:contributor:uid": 11911273,
    "_last_edit:changeset": 102047338,
    "_last_edit:timestamp": "2021-03-31T10:22:41Z",
    "_version_number": 3,
    "_size_classification": "medium"
   },
   "geometry": {
    "type": "Point",
    "coordinates": [
     4.3035977,
     51.09155105
    ]
   },
   "_matching_layer_id": "sport_pitch",
   "_lon": 4.3035977,
   "_lat": 51.09155105,
   "area": 652.9609475334678
  }
 ]
}