{
 "type": "FeatureCollection",
 "features": [
  {
   "type": "Feature",
   "id": "way/147561968",
   "properties": {
    "leisure": "pitch",
    "sport": "basketball",
    "id": "way/147561968",
    "_lat": "51.17390905",
    "_lon": "4.3810794",
    "_surface": "435.59633243526054",
    "_surface:ha": "0",
    "_length": "85.72504116689916",
    "_length:km": "0.1",
    "_last_edit:contributor": "lodde1949",
    "_last_edit:contributor:uid": 138772,
    "_last_edit:changeset": 10514868,
    "_last_edit:timestamp": "2012-01-27T18:16:27Z",
    "_version_number": 1,
    "_size_classification": "medium"
   },
   "geometry": {
    "type": "Point",
    "coordinates": [
     4.3810794,
     51.17390905
    ]
   },
   "_matching_layer_id": "sport_pitch",
   "_lon": 4.3810794,
   "_lat": 51.17390905,
   "area": 435.59633243526054
  },
  {
   "type": "Feature",
   "id": "way/147561972",
   "properties": {
    "leisure": "pitch",
    "name": "V.K. Valaarhof",
    "sport": "soccer",
    "id": "way/147561972",
    "_lat": "51.1744752",
    "_lon": "4.381233099999999",
    "_surface": "6017.466387236359",
    "_surface:ha": "0.6",
    "_length": "320.1091116806308",
    "_length:km": "0.3",
    "_last_edit:contributor": "dderycker",
    "_last_edit:contributor:uid": 2221769,
    "_last_edit:changeset": 74470773,
    "_last_edit:timestamp": "2019-09-14T11:48:53Z",
    "_version_number": 2,
    "_size_classification": "large"
   },
   "geometry": {
    "type": "Point",
    "coordinates": [
     4.381233099999999,
     51.1744752
    ]
   },
   "_matching_layer_id": "sport_pitch",
   "_lon": 4.381233099999999,
   "_lat": 51.1744752,
   "area": 6017.466387236359
  },
  {
   "type": "Feature",
   "id": "way/187796530",
   "properties": {
    "leisure": "pitch",
    "sport": "basketball",
    "id": "way/187796530",
    "_lat": "51.177316700000006",
    "_lon": "4.3744177",
    "_surface": "229.1330591908777",
    "_surface:ha": "0",
    "_length": "60.88086749168183",
    "_length:km": "0.1",
    "_last_edit:contributor": "EnriceV",
    "_last_edit:contributor:uid": 514888,
    "_last_edit:changeset": 13638343,
    "_last_edit:timestamp": "2012-10-26T13:59:04Z",
    "_version_number": 1,
    "_size_classification": "medium"
   },
   "geometry": {
    "type": "Point",
    "coordinates": [
     4.3744177,
     51.177316700000006
    ]
   },
   "_matching_layer_id": "sport_pitch",
   "_lon": 4.3744177,
   "_lat": 51.177316700000006,
   "area": 229.1330591908777
  },
  {
   "type": "Feature",
   "id": "way/192053940",
   "properties": {
    "leisure": "pitch",
    "id": "way/192053940",
    "_lat": "51.173481550000005",
    "_lon": "4.38567835",
    "_surface": "8280.103409084602",
    "_surface:ha": "0.8",
    "_length": "339.6475718533361",
    "_length:km": "0.3",
    "_last_edit:contributor": "EnriceV",
    "_last_edit:contributor:uid": 514888,
    "_last_edit:changeset": 13983140,
    "_last_edit:timestamp": "2012-11-22T09:40:51Z",
    "_version_number": 1,
    "_size_classification": "large"
   },
   "geometry": {
    "type": "Point",
    "coordinates": [
     4.38567835,
     51.173481550000005
    ]
   },
   "_matching_layer_id": "sport_pitch",
   "_lon": 4.38567835,
   "_lat": 51.173481550000005,
   "area": 8280.103409084602
  },
  {
   "type": "Feature",
   "id": "way/442903179",
   "properties": {
    "leisure": "pitch",
    "sport": "basketball",
    "id": "way/442903179",
    "_lat": "51.1700277",
    "_lon": "4.3938393",
    "_surface": "425.5823430353726",
    "_surface:ha": "0",
    "_length": "86.36813776934636",
    "_length:km": "0.1",
    "_last_edit:contributor": "Jakka",
    "_last_edit:contributor:uid": 2403313,
    "_last_edit:changeset": 42224362,
    "_last_edit:timestamp": "2016-09-17T10:56:32Z",
    "_version_number": 1,
    "_size_classification": "medium"
   },
   "geometry": {
    "type": "Point",
    "coordinates": [
     4.3938393,
     51.1700277
    ]
   },
   "_matching_layer_id": "sport_pitch",
   "_lon": 4.3938393,
   "_lat": 51.1700277,
   "area": 425.5823430353726
  },
  {
   "type": "Feature",
   "id": "way/863895859",
   "properties": {
    "access": "private",
    "boules": "petanque",
    "leisure": "pitch",
    "lit": "no",
    "sport": "boules",
    "surface": "sand",
    "id": "way/863895859",
    "_lat": "51.1691948",
    "_lon": "4.3793678",
    "_surface": "44.17432568122421",
    "_surface:ha": "0",
    "_length": "34.903686161092594",
    "_length:km": "0.0",
    "_last_edit:contributor": "H4N5-antw",
    "_last_edit:contributor:uid": 10846743,
    "_last_edit:changeset": 93077928,
    "_last_edit:timestamp": "2020-10-26T19:41:43Z",
    "_version_number": 1,
    "_size_classification": "small"
   },
   "geometry": {
    "type": "Point",
    "coordinates": [
     4.3793678,
     51.1691948
    ]
   },
   "_matching_layer_id": "sport_pitch",
   "_lon": 4.3793678,
   "_lat": 51.1691948,
   "area": 44.17432568122421
  }
 ]
}